Metadata-Version: 1.0
Name: louis-distributions
Version: 0.1
Summary: Gaussian and Binomial distributions
Home-page: UNKNOWN
Author: Louis Brutton
Author-email: louisbrutton@gmail.com
License: UNKNOWN
Platform: UNKNOWN
